freeflux/__init__.py
freeflux/analysis/__init__.py
freeflux/analysis/fit.py
freeflux/analysis/inst_fit.py
freeflux/analysis/inst_simulate.py
freeflux/analysis/simulate.py
freeflux/analysis/stats.py
freeflux/core/__init__.py
freeflux/core/emu.py
freeflux/core/mdv.py
freeflux/core/metabolite.py
freeflux/core/model.py
freeflux/core/reaction.py
freeflux/io/__init__.py
freeflux/io/inputs.py
freeflux/io/results.py
freeflux/optim/__init__.py
freeflux/optim/optim.py
freeflux/solver/__init__.py
freeflux/solver/lpsolver.py
freeflux/solver/nlpsolver.py
freeflux/utils/__init__.py
freeflux/utils/context.py
freeflux/utils/patch.py
freeflux/utils/progress.py
freeflux/utils/utils.py
freeflux-0.3.7.dist-info/licenses/LICENSE
freeflux-0.3.7.dist-info/METADATA
freeflux-0.3.7.dist-info/WHEEL
freeflux-0.3.7.dist-info/top_level.txt
freeflux-0.3.7.dist-info/RECORD
