Metadata-Version: 2.4
Name: freeflux
Version: 0.3.7
Summary: FreeFlux is a package for 13C metabolic flux analysis
Home-page: https://github.com/Chaowu88/freeflux
Author: Chao Wu
Author-email: chaowu09@gmail.com
License: GNU General Public License v3.0
Keywords: 13c,labeling pattern,metabolic flux analysis,metabolism,biology,non-linear programming,optimization,simulation
Classifier: Development Status :: 4 - Beta
Classifier: Intended Audience :: Science/Research
Classifier: Topic :: Scientific/Engineering :: Bio-Informatics
Classifier: License :: OSI Approved :: GNU General Public License v3 (GPLv3)
Classifier: Operating System :: OS Independent
Classifier: Programming Language :: Python :: 3.7
Classifier: Programming Language :: Python :: 3.8
Classifier: Programming Language :: Python :: 3.9
Classifier: Programming Language :: Python :: 3.10
Requires-Python: >=3.7
License-File: LICENSE
Requires-Dist: numpy<1.23,>=1.20
Requires-Dist: pandas~=1.0
Requires-Dist: sympy~=1.6
Requires-Dist: scipy<1.9,>=1.5
Requires-Dist: pyomo<=6.5,>=6.2
Requires-Dist: matplotlib<=3.7,>=3.2
Requires-Dist: setuptools<65
Requires-Dist: pillow
Requires-Dist: xlrd==1.2.0
Requires-Dist: openpyxl
Dynamic: license-file
